README
setup.py
./nrdpy/__init__.py
./nrdpy/api.py
./nrdpy/result.py
nrdpy.egg-info/PKG-INFO
nrdpy.egg-info/SOURCES.txt
nrdpy.egg-info/dependency_links.txt
nrdpy.egg-info/requires.txt
nrdpy.egg-info/top_level.txt