Metadata-Version: 1.0
Name: nrdpy
Version: 0.9.0
Summary: A library for submitting passive checks to Nagios NRDP endpoints
Home-page: https://github.com/AlexForster/nrdpy
Author: Alex Forster
Author-email: alex@alexforster.com
License: 3-Clause ("New") BSD license
Platform: UNKNOWN
